syncopate/__init__.py
syncopate/main.py
syncopate/combinators/__init__.py
syncopate/combinators/_parallelize.py
syncopate/combinators/collector.py
syncopate/combinators/tap.py
syncopate-0.1.4.dist-info/METADATA
syncopate-0.1.4.dist-info/WHEEL
syncopate-0.1.4.dist-info/top_level.txt
syncopate-0.1.4.dist-info/RECORD
