Metadata-Version: 2.1
Name: syncopate
Version: 0.1.4
Summary: Pure asynchronous orchestrations
Author-email: Marcel Claramunt <marcel@moveread.com>
Requires-Python: >=3.10
Requires-Dist: haskellian
